LICENSE
MANIFEST.in
readme.md
requirements.txt
setup.py
FluentGenerator/__init__.py
FluentGenerator/template.html
FluentGenerator.egg-info/PKG-INFO
FluentGenerator.egg-info/SOURCES.txt
FluentGenerator.egg-info/dependency_links.txt
FluentGenerator.egg-info/requires.txt
FluentGenerator.egg-info/top_level.txt
FluentGenerator/utils/__init__.py