Metadata-Version: 2.1
Name: FluentGenerator
Version: 2022.2.2.2
Summary: Create a random fluent image based on multiple colors.
Home-page: https://github.com/ulbwazhine/FluentGenerator
Author: Ulbwazhine
Author-email: ulbwa@icloud.com
License: MIT
Platform: UNKNOWN
License-File: LICENSE
